{"payment_id":"8f9c8b33-178e-45d2-92ae-8ba9c4d992e9","trace_id":"1b224e64-fca8-42f2-8439-8a41acffe1b2","verdict":"suspicious","assigned_team":"legal","risk_score":42.9,"rule_score":0.0,"pattern_score":27.0,"llm_risk_score":75.0,"justification":"Transaction flagged for review (Risk Score: 42.9/100)\n\nDetected Patterns (1):- high_risk_jurisdiction: Transaction involves high-risk jurisdiction: IR -> GB\n\nLLM Identified Patterns (3):- high_risk_jurisdiction: Originator from Iran (IR) conducting large-value securities trade through Singapore channel- round_amounts: Amount 466640.72 CHF appears artificially precise, potentially structured to avoid round-number detection- narrative_mismatch: Purpose code SAL (salary) inconsistent with securities_trade product type and large amount\n\nLLM Flagged Transactions (1):- 01438d7c-8754-4b60-92d6-abbdcecde07c: High-risk jurisdiction (Iran) originator with large securities trade; potential sanctions evasion risk despite screening PASS\n\nLLM Assessment Summary:\nSingle transaction flagged for high-risk jurisdiction (Iran originator) conducting unusually large securities trade via Singapore channel. Purpose code mismatch and artificially precise amount suggest potential layering or structuring activity requiring enhanced due diligence despite sanctions screening pass.\n\nScoring Breakdown:- Rule Score: 0.0/100 (30% weight)- Pattern Score: 27.0/100 (20% weight)- LLM Risk Score: 75.0/100 (50% weight)\n\nAssigned to Legal team due to sanctions, PEP, or regulatory concerns","triggered_rules":[],"detected_patterns":[{"pattern_type":"high_risk_jurisdiction","description":"Transaction involves high-risk jurisdiction: IR -> GB","severity":"high","confidence":0.9,"pattern_score":30.0}],"llm_flagged_transactions":[{"transaction_id":"01438d7c-8754-4b60-92d6-abbdcecde07c","reason":"High-risk jurisdiction (Iran) originator with large securities trade; potential sanctions evasion risk despite screening PASS","risk_level":"High"}],"llm_patterns":[{"pattern_type":"high_risk_jurisdiction","description":"Originator from Iran (IR) conducting large-value securities trade through Singapore channel","affected_transactions":["01438d7c-8754-4b60-92d6-abbdcecde07c"],"severity":"High"},{"pattern_type":"round_amounts","description":"Amount 466640.72 CHF appears artificially precise, potentially structured to avoid round-number detection","affected_transactions":["01438d7c-8754-4b60-92d6-abbdcecde07c"],"severity":"Medium"},{"pattern_type":"narrative_mismatch","description":"Purpose code SAL (salary) inconsistent with securities_trade product type and large amount","affected_transactions":["01438d7c-8754-4b60-92d6-abbdcecde07c"],"severity":"Medium"}],"llm_summary":"Single transaction flagged for high-risk jurisdiction (Iran originator) conducting unusually large securities trade via Singapore channel. Purpose code mismatch and artificially precise amount suggest potential layering or structuring activity requiring enhanced due diligence despite sanctions screening pass.","analysis_duration_ms":3148,"alert_id":"8988b281-1706-4640-bc08-9138257eff23","verdict_id":"1b224e64-fca8-42f2-8439-8a41acffe1b2"}